BeginnersbookShujukuxitongJiaochengChuyi/README.md
BeginnersbookShujukuxitongJiaochengChuyi/__init__.py
BeginnersbookShujukuxitongJiaochengChuyi/__main__.py
BeginnersbookShujukuxitongJiaochengChuyi/file.epub
BeginnersbookShujukuxitongJiaochengChuyi/index.html
BeginnersbookShujukuxitongJiaochengChuyi/css/__init__.py
BeginnersbookShujukuxitongJiaochengChuyi/css/annotations.css
BeginnersbookShujukuxitongJiaochengChuyi/css/main.css
BeginnersbookShujukuxitongJiaochengChuyi/css/normalize.css
BeginnersbookShujukuxitongJiaochengChuyi/css/popup.css
BeginnersbookShujukuxitongJiaochengChuyi/font/__init__.py
BeginnersbookShujukuxitongJiaochengChuyi/font/fontello.eot
BeginnersbookShujukuxitongJiaochengChuyi/font/fontello.svg
BeginnersbookShujukuxitongJiaochengChuyi/font/fontello.ttf
BeginnersbookShujukuxitongJiaochengChuyi/font/fontello.woff
BeginnersbookShujukuxitongJiaochengChuyi/img/__init__.py
BeginnersbookShujukuxitongJiaochengChuyi/img/annotator-glyph-sprite.png
BeginnersbookShujukuxitongJiaochengChuyi/img/annotator-icon-sprite.png
BeginnersbookShujukuxitongJiaochengChuyi/img/apple-touch-icon.png
BeginnersbookShujukuxitongJiaochengChuyi/img/cancelfullscreen.png
BeginnersbookShujukuxitongJiaochengChuyi/img/close.png
BeginnersbookShujukuxitongJiaochengChuyi/img/fullscreen.png
BeginnersbookShujukuxitongJiaochengChuyi/img/loader.gif
BeginnersbookShujukuxitongJiaochengChuyi/img/menu-icon.png
BeginnersbookShujukuxitongJiaochengChuyi/img/save.png
BeginnersbookShujukuxitongJiaochengChuyi/img/saved.png
BeginnersbookShujukuxitongJiaochengChuyi/img/settings-s.png
BeginnersbookShujukuxitongJiaochengChuyi/img/settings.png
BeginnersbookShujukuxitongJiaochengChuyi/img/star.png
BeginnersbookShujukuxitongJiaochengChuyi/js/__init__.py
BeginnersbookShujukuxitongJiaochengChuyi/js/epub.js
BeginnersbookShujukuxitongJiaochengChuyi/js/epub.min.js
BeginnersbookShujukuxitongJiaochengChuyi/js/epub.min.map
BeginnersbookShujukuxitongJiaochengChuyi/js/hooks.min.js
beginnersbook_shujukuxitong_jiaocheng_chuyi-2024.3.5.0.dist-info/METADATA
beginnersbook_shujukuxitong_jiaocheng_chuyi-2024.3.5.0.dist-info/WHEEL
beginnersbook_shujukuxitong_jiaocheng_chuyi-2024.3.5.0.dist-info/entry_points.txt
beginnersbook_shujukuxitong_jiaocheng_chuyi-2024.3.5.0.dist-info/top_level.txt
beginnersbook_shujukuxitong_jiaocheng_chuyi-2024.3.5.0.dist-info/RECORD
